boost_filesystem-vc143-mt-x64-1_86.dll
boost_iostreams-vc143-mt-x64-1_86.dll
boost_thread-vc143-mt-x64-1_86.dll
brotlicommon.dll
brotlidec.dll
bz2.dll
double-conversion.dll
fmt.dll
freetype.dll
glew32.dll
grasp_pose_generator.cp312-win_amd64.pyd
jpeg62.dll
libexpat.dll
liblzma.dll
libpng16.dll
lz4.dll
pcl_common.dll
pcl_features.dll
pcl_filters.dll
pcl_io.dll
pcl_io_ply.dll
pcl_kdtree.dll
pcl_ml.dll
pcl_octree.dll
pcl_sample_consensus.dll
pcl_search.dll
pcl_segmentation.dll
pcl_visualization.dll
pugixml.dll
tiff.dll
verdict.dll
vtkChartsCore-9.3.dll
vtkCommonColor-9.3.dll
vtkCommonComputationalGeometry-9.3.dll
vtkCommonCore-9.3.dll
vtkCommonDataModel-9.3.dll
vtkCommonExecutionModel-9.3.dll
vtkCommonMath-9.3.dll
vtkCommonMisc-9.3.dll
vtkCommonSystem-9.3.dll
vtkCommonTransforms-9.3.dll
vtkDICOMParser-9.3.dll
vtkFiltersCore-9.3.dll
vtkFiltersExtraction-9.3.dll
vtkFiltersGeneral-9.3.dll
vtkFiltersGeometry-9.3.dll
vtkFiltersHybrid-9.3.dll
vtkFiltersHyperTree-9.3.dll
vtkFiltersModeling-9.3.dll
vtkFiltersSources-9.3.dll
vtkFiltersStatistics-9.3.dll
vtkFiltersTexture-9.3.dll
vtkFiltersVerdict-9.3.dll
vtkIOCore-9.3.dll
vtkIOGeometry-9.3.dll
vtkIOImage-9.3.dll
vtkIOLegacy-9.3.dll
vtkIOPLY-9.3.dll
vtkIOXML-9.3.dll
vtkIOXMLParser-9.3.dll
vtkImagingColor-9.3.dll
vtkImagingCore-9.3.dll
vtkImagingGeneral-9.3.dll
vtkImagingHybrid-9.3.dll
vtkImagingSources-9.3.dll
vtkInfovisCore-9.3.dll
vtkInteractionStyle-9.3.dll
vtkInteractionWidgets-9.3.dll
vtkParallelCore-9.3.dll
vtkParallelDIY-9.3.dll
vtkRenderingAnnotation-9.3.dll
vtkRenderingContext2D-9.3.dll
vtkRenderingContextOpenGL2-9.3.dll
vtkRenderingCore-9.3.dll
vtkRenderingFreeType-9.3.dll
vtkRenderingHyperTreeGrid-9.3.dll
vtkRenderingLOD-9.3.dll
vtkRenderingOpenGL2-9.3.dll
vtkRenderingUI-9.3.dll
vtkViewsContext2D-9.3.dll
vtkViewsCore-9.3.dll
vtkkissfft-9.3.dll
vtkloguru-9.3.dll
vtkmetaio-9.3.dll
vtksys-9.3.dll
vtktoken-9.3.dll
zlib1.dll
zstd.dll
grasp_pose_generator-1.0.1.dist-info/METADATA
grasp_pose_generator-1.0.1.dist-info/WHEEL
grasp_pose_generator-1.0.1.dist-info/top_level.txt
grasp_pose_generator-1.0.1.dist-info/RECORD
