Metadata-Version: 2.4
Name: grasp_pose_generator
Version: 1.0.1
Summary: A binding of gpg using pybind11 and CMake
Author: AliReza Beigy
Author-email: AliRezaBeigyKhu@gmail.com
License: MIT
Platform: nt
Platform: posix
Requires-Python: >=3.11
Dynamic: author
Dynamic: author-email
Dynamic: description
Dynamic: description-content-type
Dynamic: license
Dynamic: platform
Dynamic: requires-python
Dynamic: summary
